writescore/__init__.py
writescore/__version__.py
writescore/cli/__init__.py
writescore/cli/args.py
writescore/cli/formatters.py
writescore/cli/main.py
writescore/core/__init__.py
writescore/core/analysis_config.py
writescore/core/analyzer.py
writescore/core/config_loader.py
writescore/core/config_registry.py
writescore/core/config_schema.py
writescore/core/dataset.py
writescore/core/deployment.py
writescore/core/dimension_loader.py
writescore/core/dimension_registry.py
writescore/core/distribution_analyzer.py
writescore/core/dynamic_reporter.py
writescore/core/exceptions.py
writescore/core/interpretability.py
writescore/core/normality.py
writescore/core/parameter_derivation.py
writescore/core/parameter_loader.py
writescore/core/parameters.py
writescore/core/recalibration.py
writescore/core/results.py
writescore/core/validation.py
writescore/core/weight_mediator.py
writescore/data/brysbaert_concreteness_raw.txt
writescore/data/idiom_lexicon.json
writescore/data/idiom_lexicon.txt
writescore/dimensions/__init__.py
writescore/dimensions/advanced_lexical.py
writescore/dimensions/ai_vocabulary.py
writescore/dimensions/base.py
writescore/dimensions/base_strategy.py
writescore/dimensions/burstiness.py
writescore/dimensions/energy.py
writescore/dimensions/figurative_language.py
writescore/dimensions/formatting.py
writescore/dimensions/lexical.py
writescore/dimensions/perplexity.py
writescore/dimensions/pragmatic_markers.py
writescore/dimensions/predictability.py
writescore/dimensions/readability.py
writescore/dimensions/semantic_coherence.py
writescore/dimensions/sentiment.py
writescore/dimensions/structure.py
writescore/dimensions/syntactic.py
writescore/dimensions/transition_marker.py
writescore/dimensions/voice.py
writescore/evidence/__init__.py
writescore/history/__init__.py
writescore/history/export.py
writescore/history/tracker.py
writescore/history/trends.py
writescore/scoring/__init__.py
writescore/scoring/domain_thresholds.py
writescore/scoring/dual_score.py
writescore-6.5.0.dist-info/licenses/LICENSE
writescore-6.5.0.dist-info/METADATA
writescore-6.5.0.dist-info/WHEEL
writescore-6.5.0.dist-info/entry_points.txt
writescore-6.5.0.dist-info/top_level.txt
writescore-6.5.0.dist-info/RECORD
