Metadata-Version: 2.4
Name: writescore
Version: 6.5.0
Summary: AI writing pattern analysis and scoring tool
Author: BOHICA Labs
License: MIT
Project-URL: Homepage, https://github.com/BOHICA-LABS/writescore
Project-URL: Repository, https://github.com/BOHICA-LABS/writescore
Project-URL: Documentation, https://github.com/BOHICA-LABS/writescore#readme
Project-URL: Issues, https://github.com/BOHICA-LABS/writescore/issues
Classifier: Development Status :: 4 - Beta
Classifier: Intended Audience :: Developers
Classifier: Topic :: Text Processing :: Linguistic
Classifier: License :: OSI Approved :: MIT License
Classifier: Programming Language :: Python :: 3
Classifier: Programming Language :: Python :: 3.9
Classifier: Programming Language :: Python :: 3.10
Classifier: Programming Language :: Python :: 3.11
Classifier: Programming Language :: Python :: 3.12
Requires-Python: >=3.9
License-File: LICENSE
Requires-Dist: marko>=2.0.0
Requires-Dist: nltk>=3.8
Requires-Dist: spacy>=3.7.0
Requires-Dist: textstat>=0.7.3
Requires-Dist: transformers>=4.35.0
Requires-Dist: torch>=2.0.0
Requires-Dist: scikit-learn>=1.3.0
Requires-Dist: scipy>=1.11.0
Requires-Dist: scikit-learn>=1.3.0
Requires-Dist: textacy>=0.13.0
Requires-Dist: numpy>=1.24.0
Requires-Dist: click>=8.0.0
Provides-Extra: dev
Requires-Dist: pytest>=7.4.0; extra == "dev"
Requires-Dist: pytest-cov>=4.1.0; extra == "dev"
Requires-Dist: pytest-timeout>=2.2.0; extra == "dev"
Requires-Dist: psutil>=5.9.0; extra == "dev"
Requires-Dist: ruff>=0.1.0; extra == "dev"
Requires-Dist: pre-commit>=3.5.0; extra == "dev"
Requires-Dist: sentence-transformers>=2.0.0; extra == "dev"
Requires-Dist: types-PyYAML>=6.0.0; extra == "dev"
Requires-Dist: pyinstaller>=6.0.0; extra == "dev"
Provides-Extra: semantic
Requires-Dist: sentence-transformers>=2.0.0; extra == "semantic"
Provides-Extra: ml
Requires-Dist: accelerate>=0.20.0; extra == "ml"
Requires-Dist: datasets>=2.14.0; extra == "ml"
Dynamic: license-file
